odoo/addons/model_serializer/README.rst
odoo/addons/model_serializer/__init__.py
odoo/addons/model_serializer/__manifest__.py
odoo/addons/model_serializer/builder.py
odoo/addons/model_serializer/core.py
odoo/addons/model_serializer/field_converter.py
odoo/addons/model_serializer/serializers.py
odoo/addons/model_serializer/i18n/es.po
odoo/addons/model_serializer/i18n/model_serializer.pot
odoo/addons/model_serializer/readme/CONTRIBUTORS.rst
odoo/addons/model_serializer/readme/DESCRIPTION.rst
odoo/addons/model_serializer/readme/HISTORY.rst
odoo/addons/model_serializer/readme/USAGE.rst
odoo/addons/model_serializer/static/description/icon.png
odoo/addons/model_serializer/static/description/index.html
odoo/addons/model_serializer/tests/__init__.py
odoo/addons/model_serializer/tests/test_model_serializer.py
odoo13_addon_model_serializer-13.0.1.0.1.dev18.dist-info/METADATA
odoo13_addon_model_serializer-13.0.1.0.1.dev18.dist-info/WHEEL
odoo13_addon_model_serializer-13.0.1.0.1.dev18.dist-info/top_level.txt
odoo13_addon_model_serializer-13.0.1.0.1.dev18.dist-info/RECORD
