Metadata-Version: 2.1
Name: odoo13-addon-model-serializer
Version: 13.0.1.0.1.dev18
Summary: Automatically translate Odoo models into Datamodels for (de)serialization
Home-page: https://github.com/OCA/rest-framework
Author: Wakari, Odoo Community Association (OCA)
Author-email: support@odoo-community.org
License: LGPL-3
Platform: UNKNOWN
Classifier: Programming Language :: Python
Classifier: Framework :: Odoo
Classifier: Framework :: Odoo :: 13.0
Classifier: License :: OSI Approved :: GNU Lesser General Public License v3 (LGPLv3)
Classifier: Development Status :: 3 - Alpha
Requires-Python: >=3.5
Requires-Dist: odoo13-addon-datamodel
Requires-Dist: odoo <13.1dev,>=13.0a
